photonlibpy/__init__.py
photonlibpy/estimatedRobotPose.py
photonlibpy/packet.py
photonlibpy/photonCamera.py
photonlibpy/photonPoseEstimator.py
photonlibpy/py.typed
photonlibpy/version.py
photonlibpy/estimation/__init__.py
photonlibpy/estimation/cameraTargetRelation.py
photonlibpy/estimation/openCVHelp.py
photonlibpy/estimation/rotTrlTransform3d.py
photonlibpy/estimation/targetModel.py
photonlibpy/estimation/visionEstimation.py
photonlibpy/generated/MultiTargetPNPResultSerde.py
photonlibpy/generated/PhotonPipelineMetadataSerde.py
photonlibpy/generated/PhotonPipelineResultSerde.py
photonlibpy/generated/PhotonTrackedTargetSerde.py
photonlibpy/generated/PnpResultSerde.py
photonlibpy/generated/TargetCornerSerde.py
photonlibpy/generated/__init__.py
photonlibpy/networktables/NTTopicSet.py
photonlibpy/networktables/__init__.py
photonlibpy/simulation/__init__.py
photonlibpy/simulation/photonCameraSim.py
photonlibpy/simulation/simCameraProperties.py
photonlibpy/simulation/videoSimUtil.py
photonlibpy/simulation/visionSystemSim.py
photonlibpy/simulation/visionTargetSim.py
photonlibpy/targeting/TargetCorner.py
photonlibpy/targeting/__init__.py
photonlibpy/targeting/multiTargetPNPResult.py
photonlibpy/targeting/photonPipelineResult.py
photonlibpy/targeting/photonTrackedTarget.py
photonlibpy/timesync/__init__.py
photonlibpy/timesync/timeSyncServer.py
photonlibpy-2026.1.1.dist-info/METADATA
photonlibpy-2026.1.1.dist-info/WHEEL
photonlibpy-2026.1.1.dist-info/top_level.txt
photonlibpy-2026.1.1.dist-info/RECORD
