Metadata-Version: 2.4
Name: photonlibpy
Version: 2026.1.1
Summary: Pure-python implementation of PhotonLib for interfacing with PhotonVision on coprocessors. Implemented with PhotonVision version v2026.1.1 .
Home-page: https://photonvision.org
Author: Photonvision Development Team
Classifier: License :: OSI Approved :: MIT License
Requires-Dist: numpy~=2.3
Requires-Dist: wpilib<2027,>=2026.2.1
Requires-Dist: robotpy-wpimath<2027,>=2026.2.1
Requires-Dist: robotpy-apriltag<2027,>=2026.2.1
Requires-Dist: robotpy-cscore<2027,>=2026.2.1
Requires-Dist: pyntcore<2027,>=2026.2.1
Requires-Dist: opencv-python; platform_machine != "roborio"
Dynamic: author
Dynamic: classifier
Dynamic: description
Dynamic: description-content-type
Dynamic: home-page
Dynamic: requires-dist
Dynamic: summary
